Kuai-0.1.3.dist-info/DESCRIPTION.rst
Kuai-0.1.3.dist-info/METADATA
Kuai-0.1.3.dist-info/RECORD
Kuai-0.1.3.dist-info/WHEEL
Kuai-0.1.3.dist-info/metadata.json
Kuai-0.1.3.dist-info/top_level.txt
kuai/__init__.py
kuai/helpers.py
kuai/backends/__init__.py
kuai/backends/priority.py
kuai/backends/signal.py
kuai/backends/simple.py
kuai/backends/threaded.py
kuai/backends/threadpool.py
