Metadata-Version: 2.0
Name: Kuai
Version: 0.1.3
Summary: Simple & fast event library. MIT licensed
Home-page: https://github.com/Duroktar/kuai
Author: Scott Doucet
Author-email: duroktar@gmail.com
License: MIT license
Keywords: kuai
Platform: UNKNOWN
Classifier: Development Status :: 2 - Pre-Alpha
Classifier: Intended Audience :: Developers
Classifier: License :: OSI Approved :: MIT License
Classifier: Natural Language :: English
Classifier: Programming Language :: Python :: 3.5
Classifier: Programming Language :: Python :: 3.6
Requires-Dist: pluginbase
